dschain/__init__.py
dschain-0.0.1.dist-info/LICENSE
dschain-0.0.1.dist-info/METADATA
dschain-0.0.1.dist-info/WHEEL
dschain-0.0.1.dist-info/RECORD
