Metadata-Version: 2.1
Name: dschain
Version: 0.0.1
Summary: bring the power of LLMs inside your jupyter notebooks
License: MIT
Author: Aarshay Jain
Author-email: aarshay@thismlguy.com
Requires-Python: >3.8.1,<4
Classifier: License :: OSI Approved :: MIT License
Classifier: Programming Language :: Python :: 3
Classifier: Programming Language :: Python :: 3.9
Classifier: Programming Language :: Python :: 3.10
Classifier: Programming Language :: Python :: 3.11
Requires-Dist: langchain (>=0.0.177,<0.0.178)
